{
  "id": 132157,
  "referenceId": 108211,
  "name": "Peace",
  "localizedName": "Peace",
  "content": [
    {
      "tiptap": {
        "type": "doc",
        "content": [
          {
            "type": "paragraph",
            "attrs": {
              "class": null
            },
            "content": [
              {
                "type": "text",
                "text": "The word for peace in the Hebrew language is shalom. It means more than a time when there is no fighting or war. It means that there is safety, health and justice. It means that everyone has enough of what they need. It means that relationships are whole and healthy. They are the way God wants them to be. This includes each person being at peace with God. It also includes the relationships between people and everything else that God created."
              }
            ]
          }
        ]
      }
    }
  ],
  "grouping": {
    "type": "Dictionary",
    "name": "Key Terms (Biblica)",
    "mediaType": "Text",
    "licenseInfo": {
      "title": "Biblica Bible Dictionary",
      "copyright": {
        "dates": "2023",
        "holder": {
          "name": "Biblica, Inc.",
          "url": "https://www.biblica.com/"
        }
      },
      "licenses": [
        {
          "eng": {
            "name": "CC BY-SA 4.0 license",
            "url": "https://creativecommons.org/licenses/by-sa/4.0/legalcode.en"
          }
        }
      ],
      "showAdaptationNoticeForEnglish": false,
      "showAdaptationNoticeForNonEnglish": true
    }
  },
  "language": {
    "id": 1,
    "code": "eng",
    "displayName": "English",
    "scriptDirection": "LTR"
  }
}