{
  "id": 132895,
  "referenceId": 108949,
  "name": "2 Corinthians 11:1–15",
  "localizedName": "2 Corinthians 11:1–15",
  "content": [
    {
      "tiptap": {
        "type": "doc",
        "content": [
          {
            "type": "paragraph",
            "content": [
              {
                "type": "text",
                "text": "In the "
              },
              {
                "type": "text",
                "marks": [
                  {
                    "type": "resourceReference",
                    "attrs": {
                      "resourceId": "108207",
                      "resourceType": "BiblicaStudyNotesKeyTerms"
                    }
                  }
                ],
                "text": "Garden of Eden"
              },
              {
                "type": "text",
                "text": ", the snake told "
              },
              {
                "type": "text",
                "marks": [
                  {
                    "type": "resourceReference",
                    "attrs": {
                      "resourceId": "108205",
                      "resourceType": "BiblicaStudyNotesKeyTerms"
                    }
                  }
                ],
                "text": "Eve"
              },
              {
                "type": "text",
                "text": " lies about God. She believed them."
              }
            ]
          },
          {
            "type": "paragraph",
            "content": [
              {
                "type": "text",
                "text": "Paul didn’t want the Corinthian believers to be tricked by lies about God. False teachers that Paul called "
              },
              {
                "type": "text",
                "marks": [
                  {
                    "type": "resourceReference",
                    "attrs": {
                      "resourceId": "108153",
                      "resourceType": "BiblicaStudyNotesKeyTerms"
                    }
                  }
                ],
                "text": "super-apostles"
              },
              {
                "type": "text",
                "text": " caused trouble in the Corinthian church. They taught things that weren’t true about Jesus and the Holy Spirit."
              }
            ]
          },
          {
            "type": "paragraph",
            "content": [
              {
                "type": "text",
                "text": "Paul wanted the Corinthian believers to stay faithful to Jesus. Paul had taught them the truth about Jesus when he was with them. He hadn’t done it to earn money. The Corinthian believers hadn’t given him anything for his work among them. Paul did it because he loved them."
              }
            ]
          }
        ]
      }
    }
  ],
  "grouping": {
    "type": "StudyNotes",
    "name": "Study Notes (Biblica)",
    "mediaType": "Text",
    "licenseInfo": {
      "title": "Biblica Study Notes",
      "copyright": {
        "dates": "2023",
        "holder": {
          "name": "Biblica Inc.",
          "url": "https://www.biblica.com/"
        }
      },
      "licenses": [
        {
          "eng": {
            "name": "CC BY-SA 4.0 license",
            "url": "https://creativecommons.org/licenses/by-sa/4.0/legalcode.en"
          }
        }
      ],
      "showAdaptationNoticeForEnglish": false,
      "showAdaptationNoticeForNonEnglish": true
    }
  },
  "language": {
    "id": 1,
    "code": "eng",
    "displayName": "English",
    "scriptDirection": "LTR"
  }
}