{
  "id": 132909,
  "referenceId": 108963,
  "name": "Galatians 5:13–26",
  "localizedName": "Galatians 5:13–26",
  "content": [
    {
      "tiptap": {
        "type": "doc",
        "content": [
          {
            "type": "paragraph",
            "content": [
              {
                "type": "text",
                "text": "Paul explained how the Galatian believers should use their freedom. Being free from the law didn’t mean that the Galatians could do anything they wanted to do. It meant that they were free to obey God and to serve others out of love."
              }
            ]
          },
          {
            "type": "paragraph",
            "content": [
              {
                "type": "text",
                "text": "Paul explained that there are two ways to live. One way is to be controlled by sin. This leads people to do evil things that harm others and themselves. These evil ways have no place in the "
              },
              {
                "type": "text",
                "marks": [
                  {
                    "type": "resourceReference",
                    "attrs": {
                      "resourceId": "108561",
                      "resourceType": "BiblicaStudyNotesKeyTerms"
                    }
                  }
                ],
                "text": "kingdom of God"
              },
              {
                "type": "text",
                "text": "."
              }
            ]
          },
          {
            "type": "paragraph",
            "content": [
              {
                "type": "text",
                "text": "The other way to live is to be led by the Holy Spirit. The Spirit leads people to say no to everything that goes against what God wants. The Spirit leads people to follow Jesus’ example. This is seen in the way that people think, speak and act."
              }
            ]
          },
          {
            "type": "paragraph",
            "content": [
              {
                "type": "text",
                "text": "Paul had a name for the ways of thinking, speaking and acting like Jesus. He called them the "
              },
              {
                "type": "text",
                "marks": [
                  {
                    "type": "resourceReference",
                    "attrs": {
                      "resourceId": "108154",
                      "resourceType": "BiblicaStudyNotesKeyTerms"
                    }
                  }
                ],
                "text": "fruit of the Holy Spirit"
              },
              {
                "type": "text",
                "text": ". These ways don’t depend on rules that control people from the outside. They are the result of the Holy Spirit changing a person’s "
              },
              {
                "type": "text",
                "marks": [
                  {
                    "type": "resourceReference",
                    "attrs": {
                      "resourceId": "108419",
                      "resourceType": "BiblicaStudyNotesKeyTerms"
                    }
                  }
                ],
                "text": "heart"
              },
              {
                "type": "text",
                "text": "."
              }
            ]
          }
        ]
      }
    }
  ],
  "grouping": {
    "type": "StudyNotes",
    "name": "Study Notes (Biblica)",
    "mediaType": "Text",
    "licenseInfo": {
      "title": "Biblica Study Notes",
      "copyright": {
        "dates": "2023",
        "holder": {
          "name": "Biblica Inc.",
          "url": "https://www.biblica.com/"
        }
      },
      "licenses": [
        {
          "eng": {
            "name": "CC BY-SA 4.0 license",
            "url": "https://creativecommons.org/licenses/by-sa/4.0/legalcode.en"
          }
        }
      ],
      "showAdaptationNoticeForEnglish": false,
      "showAdaptationNoticeForNonEnglish": true
    }
  },
  "language": {
    "id": 1,
    "code": "eng",
    "displayName": "English",
    "scriptDirection": "LTR"
  }
}