{
  "id": 132624,
  "referenceId": 108678,
  "name": "Mark 11:1–11",
  "localizedName": "Mark 11:1–11",
  "content": [
    {
      "tiptap": {
        "type": "doc",
        "content": [
          {
            "type": "paragraph",
            "content": [
              {
                "type": "text",
                "text": "Jesus had told people many times not to talk about who he really was. But then he did something bold in public. He rode into Jerusalem as Israel’s Messiah."
              }
            ]
          },
          {
            "type": "paragraph",
            "content": [
              {
                "type": "text",
                "text": "The people cried out Hosanna! This means save us now! They wanted a kingdom like the famous King David’s kingdom. They wanted "
              },
              {
                "type": "text",
                "marks": [
                  {
                    "type": "resourceReference",
                    "attrs": {
                      "resourceId": "108196",
                      "resourceType": "BiblicaStudyNotesKeyTerms"
                    }
                  }
                ],
                "text": "salvation"
              },
              {
                "type": "text",
                "text": " from their enemies the Romans."
              }
            ]
          },
          {
            "type": "paragraph",
            "content": [
              {
                "type": "text",
                "text": "But Jesus was humble and rode a donkey instead of a war horse."
              }
            ]
          }
        ]
      }
    }
  ],
  "grouping": {
    "type": "StudyNotes",
    "name": "Study Notes (Biblica)",
    "mediaType": "Text",
    "licenseInfo": {
      "title": "Biblica Study Notes",
      "copyright": {
        "dates": "2023",
        "holder": {
          "name": "Biblica Inc.",
          "url": "https://www.biblica.com/"
        }
      },
      "licenses": [
        {
          "eng": {
            "name": "CC BY-SA 4.0 license",
            "url": "https://creativecommons.org/licenses/by-sa/4.0/legalcode.en"
          }
        }
      ],
      "showAdaptationNoticeForEnglish": false,
      "showAdaptationNoticeForNonEnglish": true
    }
  },
  "language": {
    "id": 1,
    "code": "eng",
    "displayName": "English",
    "scriptDirection": "LTR"
  }
}