{
  "id": 132926,
  "referenceId": 108980,
  "name": "Philippians 3:1–21",
  "localizedName": "Philippians 3:1–21",
  "content": [
    {
      "tiptap": {
        "type": "doc",
        "content": [
          {
            "type": "paragraph",
            "content": [
              {
                "type": "text",
                "text": "The Philippian believers could be full of joy because they belonged to the Lord. Yet some people taught that "
              },
              {
                "type": "text",
                "marks": [
                  {
                    "type": "resourceReference",
                    "attrs": {
                      "resourceId": "108547",
                      "resourceType": "BiblicaStudyNotesKeyTerms"
                    }
                  }
                ],
                "text": "Gentile"
              },
              {
                "type": "text",
                "text": " believers had to be "
              },
              {
                "type": "text",
                "marks": [
                  {
                    "type": "resourceReference",
                    "attrs": {
                      "resourceId": "108257",
                      "resourceType": "BiblicaStudyNotesKeyTerms"
                    }
                  }
                ],
                "text": "circumcised"
              },
              {
                "type": "text",
                "text": " to belong to Jesus."
              }
            ]
          },
          {
            "type": "paragraph",
            "content": [
              {
                "type": "text",
                "text": "Paul explained that people shouldn’t trust in circumcision or anything else that humans can do. Nothing that "
              },
              {
                "type": "text",
                "marks": [
                  {
                    "type": "resourceReference",
                    "attrs": {
                      "resourceId": "108202",
                      "resourceType": "BiblicaStudyNotesKeyTerms"
                    }
                  }
                ],
                "text": "human beings"
              },
              {
                "type": "text",
                "text": " do can make them "
              },
              {
                "type": "text",
                "marks": [
                  {
                    "type": "resourceReference",
                    "attrs": {
                      "resourceId": "108254",
                      "resourceType": "BiblicaStudyNotesKeyTerms"
                    }
                  }
                ],
                "text": "right with God"
              },
              {
                "type": "text",
                "text": ". Paul had done many things that made him look like an important "
              },
              {
                "type": "text",
                "marks": [
                  {
                    "type": "resourceReference",
                    "attrs": {
                      "resourceId": "108503",
                      "resourceType": "BiblicaStudyNotesKeyTerms"
                    }
                  }
                ],
                "text": "Jew"
              },
              {
                "type": "text",
                "text": ". But those things didn’t save him."
              }
            ]
          },
          {
            "type": "paragraph",
            "content": [
              {
                "type": "text",
                "text": "God saves people when they believe that Jesus is Lord and Christ. Paul had joy while he was alive because he knew Christ. He was already living as a "
              },
              {
                "type": "text",
                "marks": [
                  {
                    "type": "resourceReference",
                    "attrs": {
                      "resourceId": "108156",
                      "resourceType": "BiblicaStudyNotesKeyTerms"
                    }
                  }
                ],
                "text": "citizen of heaven"
              },
              {
                "type": "text",
                "text": ". His goal for the future was to be with Jesus for ever."
              }
            ]
          },
          {
            "type": "paragraph",
            "content": [
              {
                "type": "text",
                "text": "Jesus will return to earth from "
              },
              {
                "type": "text",
                "marks": [
                  {
                    "type": "resourceReference",
                    "attrs": {
                      "resourceId": "108201",
                      "resourceType": "BiblicaStudyNotesKeyTerms"
                    }
                  }
                ],
                "text": "heaven"
              },
              {
                "type": "text",
                "text": ". He will bring everything on earth under his control. God will raise Jesus’ followers from the dead. At the "
              },
              {
                "type": "text",
                "marks": [
                  {
                    "type": "resourceReference",
                    "attrs": {
                      "resourceId": "108568",
                      "resourceType": "BiblicaStudyNotesKeyTerms"
                    }
                  }
                ],
                "text": "resurrection"
              },
              {
                "type": "text",
                "text": " they will have new bodies like Jesus has. Paul longed for this. He wanted the Philippians to follow his example and have that goal too."
              }
            ]
          }
        ]
      }
    }
  ],
  "grouping": {
    "type": "StudyNotes",
    "name": "Study Notes (Biblica)",
    "mediaType": "Text",
    "licenseInfo": {
      "title": "Biblica Study Notes",
      "copyright": {
        "dates": "2023",
        "holder": {
          "name": "Biblica Inc.",
          "url": "https://www.biblica.com/"
        }
      },
      "licenses": [
        {
          "eng": {
            "name": "CC BY-SA 4.0 license",
            "url": "https://creativecommons.org/licenses/by-sa/4.0/legalcode.en"
          }
        }
      ],
      "showAdaptationNoticeForEnglish": false,
      "showAdaptationNoticeForNonEnglish": true
    }
  },
  "language": {
    "id": 1,
    "code": "eng",
    "displayName": "English",
    "scriptDirection": "LTR"
  }
}