{
  "id": 132852,
  "referenceId": 108906,
  "name": "Romans 15:17–33",
  "localizedName": "Romans 15:17–33",
  "content": [
    {
      "tiptap": {
        "type": "doc",
        "content": [
          {
            "type": "paragraph",
            "content": [
              {
                "type": "text",
                "text": "Near the end of his letter Paul wrote about the work he had been doing. He was grateful for what Christ had done through him. The Spirit of God was the one giving him the strength to do his work."
              }
            ]
          },
          {
            "type": "paragraph",
            "content": [
              {
                "type": "text",
                "text": "His work was to share the good news about Jesus. He shared it with people who had never heard it before. He had done this in the lands controlled by the Roman government around "
              },
              {
                "type": "text",
                "marks": [
                  {
                    "type": "resourceReference",
                    "attrs": {
                      "resourceId": "108464",
                      "resourceType": "BiblicaStudyNotesKeyTerms"
                    }
                  }
                ],
                "text": "Jerusalem"
              },
              {
                "type": "text",
                "text": "."
              }
            ]
          },
          {
            "type": "paragraph",
            "content": [
              {
                "type": "text",
                "text": "He now wanted to preach in "
              },
              {
                "type": "text",
                "marks": [
                  {
                    "type": "resourceReference",
                    "attrs": {
                      "resourceId": "108144",
                      "resourceType": "BiblicaStudyNotesKeyTerms"
                    }
                  }
                ],
                "text": "Spain"
              },
              {
                "type": "text",
                "text": ". His plan was to visit the believers in Rome on the way to Spain. He looked forward to how they could encourage one another."
              }
            ]
          },
          {
            "type": "paragraph",
            "content": [
              {
                "type": "text",
                "text": "But first he needed to go to Jerusalem. He was taking a gift of money from Gentile believers to Jewish believers in need there. Acts chapters 21 to 28 tell what happened. Paul was arrested in Jerusalem. He couldn’t make the trip to Rome and to Spain as he had planned. Yet a few years later he was sent to Rome as a prisoner. That is when he got to meet the believers in Rome."
              }
            ]
          }
        ]
      }
    }
  ],
  "grouping": {
    "type": "StudyNotes",
    "name": "Study Notes (Biblica)",
    "mediaType": "Text",
    "licenseInfo": {
      "title": "Biblica Study Notes",
      "copyright": {
        "dates": "2023",
        "holder": {
          "name": "Biblica Inc.",
          "url": "https://www.biblica.com/"
        }
      },
      "licenses": [
        {
          "eng": {
            "name": "CC BY-SA 4.0 license",
            "url": "https://creativecommons.org/licenses/by-sa/4.0/legalcode.en"
          }
        }
      ],
      "showAdaptationNoticeForEnglish": false,
      "showAdaptationNoticeForNonEnglish": true
    }
  },
  "language": {
    "id": 1,
    "code": "eng",
    "displayName": "English",
    "scriptDirection": "LTR"
  }
}