{
  "id": 132853,
  "referenceId": 108907,
  "name": "Romans 16:1–15",
  "localizedName": "Romans 16:1–15",
  "content": [
    {
      "tiptap": {
        "type": "doc",
        "content": [
          {
            "type": "paragraph",
            "content": [
              {
                "type": "text",
                "text": "Paul mentioned the names of many friends and people who worked with him. Many of these names are also found in the book of Acts and in "
              },
              {
                "type": "text",
                "marks": [
                  {
                    "type": "resourceReference",
                    "attrs": {
                      "resourceId": "108120",
                      "resourceType": "BiblicaStudyNotesKeyTerms"
                    }
                  }
                ],
                "text": "Paul’s letters"
              },
              {
                "type": "text",
                "text": "."
              }
            ]
          },
          {
            "type": "paragraph",
            "content": [
              {
                "type": "text",
                "text": "This list gives a picture of how the message about Jesus spread. Those on the list include teachers, apostles and people who welcomed others into their home."
              }
            ]
          },
          {
            "type": "paragraph",
            "content": [
              {
                "type": "text",
                "text": "The list mentions women and men and Jews and Gentiles. It includes brothers, sisters, mothers and whole families. They had suffered side by side and some had been in prison together."
              }
            ]
          },
          {
            "type": "paragraph",
            "content": [
              {
                "type": "text",
                "text": "Many different people worked together as partners and friends to share the good news. This group of very different people served the world as the body of Christ."
              }
            ]
          }
        ]
      }
    }
  ],
  "grouping": {
    "type": "StudyNotes",
    "name": "Study Notes (Biblica)",
    "mediaType": "Text",
    "licenseInfo": {
      "title": "Biblica Study Notes",
      "copyright": {
        "dates": "2023",
        "holder": {
          "name": "Biblica Inc.",
          "url": "https://www.biblica.com/"
        }
      },
      "licenses": [
        {
          "eng": {
            "name": "CC BY-SA 4.0 license",
            "url": "https://creativecommons.org/licenses/by-sa/4.0/legalcode.en"
          }
        }
      ],
      "showAdaptationNoticeForEnglish": false,
      "showAdaptationNoticeForNonEnglish": true
    }
  },
  "language": {
    "id": 1,
    "code": "eng",
    "displayName": "English",
    "scriptDirection": "LTR"
  }
}